gate/conf.py
gate/scripts.py
gate/version.py
gate/gate/init.py
gate/gate/matcher/glob.py
gate/gate/matcher/contracts/init.py
gate/gate/srv/init.py
gate/gate/srv/starlette.py
gate/gate/srv/contracts/init.py
gate/matcher/glob.py
gate/matcher/contracts/init.py
gate/srv/init.py
gate/srv/starlette.py
gate/srv/contracts/init.py
pop_gate-6.0.2.dist-info/LICENSE
pop_gate-6.0.2.dist-info/METADATA
pop_gate-6.0.2.dist-info/WHEEL
pop_gate-6.0.2.dist-info/entry_points.txt
pop_gate-6.0.2.dist-info/top_level.txt
pop_gate-6.0.2.dist-info/RECORD
